__init__.py
dcos_marathon.py
dcos_marathon-1.0.14.dist-info/DESCRIPTION.rst
dcos_marathon-1.0.14.dist-info/METADATA
dcos_marathon-1.0.14.dist-info/RECORD
dcos_marathon-1.0.14.dist-info/WHEEL
dcos_marathon-1.0.14.dist-info/metadata.json
dcos_marathon-1.0.14.dist-info/top_level.txt
