Metadata-Version: 2.0
Name: dcos-marathon
Version: 1.0.14
Summary: A DCOS Marathon API Client
Home-page: https://github.com/cpdevws/dcos_marathon
Author: Chaitanya Namburi, Kaushik C
Author-email: cpdevws@gmail.com, kaushik.chand@gmail.com
License: MIT
Platform: UNKNOWN
Classifier: Development Status :: 3 - Alpha
Classifier: Intended Audience :: Developers
Classifier: Topic :: Software Development :: Build Tools
Classifier: License :: OSI Approved :: MIT License
Classifier: Programming Language :: Python :: 2
Classifier: Programming Language :: Python :: 2.6
Classifier: Programming Language :: Python :: 2.7
Classifier: Programming Language :: Python :: 3
Classifier: Programming Language :: Python :: 3.3
Classifier: Programming Language :: Python :: 3.4
Classifier: Programming Language :: Python :: 3.5
Requires-Dist: jsonschema
Requires-Dist: marathon
